[
    {
        "category": "SUB_VIDEO",
        "settings": [
            {
                "name": "VIDEONORMALLEVEL",
                "description": "Display brightness level in % when this power plan is activated",
                "values": {
                    "ac": 40,
                    "dc": 20
                }
            },
            {
                "name": "f1fbfde2-a960-4165-9f88-50667911ce96",
                "description": "Display brightness level in % when the display gets dimmed",
                "values": {
                    "ac": 20,
                    "dc": 0
                }
            },
            {
                "name": "VIDEODIM",
                "description": "Display is dimmed after the given timeout in seconds",
                "values": {
                    "ac": 90,
                    "dc": 30
                }
            },
            {
                "name": "VIDEOIDLE",
                "description": "Turn off display after the given timeout in seconds",
                "values": {
                    "ac": 180,
                    "dc": 60
                }
            },
            {
                "name": "VIDEOCONLOCK",
                "description": "Turn off display after the given timeout in seconds when system is locked",
                "values": {
                    "ac": 30,
                    "dc": 10
                }
            }
        ]
    },
    {
        "category": "SUB_SLEEP",
        "settings": [
            {
                "name": "STANDBYIDLE",
                "description": "Timeout in seconds before system goes to sleep",
                "values": {
                    "ac": 1800,
                    "dc": 300
                }
            },
            {
                "name": "UNATTENDSLEEP",
                "description": "Timeout in seconds before system enters sleep after waking up unattended",
                "values": {
                    "ac": 60,
                    "dc": 10
                }
            },
            {
                "name": "HIBERNATEIDLE",
                "description": "Hibernate after the given timeout in seconds post sleep",
                "values": {
                    "ac": 600,
                    "dc": 300
                }
            },
            {
                "name": "RTCWAKE",
                "description": "Timed events are allowed to wake system from sleep",
                "values": {
                    "ac": 2,
                    "dc": 0
                }
            }
        ]
    },
    {
        "category": "SUB_PRESENCE",
        "settings": [
            {
                "name": "HUPRVIDEODIM",
                "description": "Dim timeout in seconds after a Presence sensor detects user as inattentive",
                "values": {
                    "ac": 10,
                    "dc": 5
                }
            },
            {
                "name": "HUPRVIDEOIDLEINATTENTIVE",
                "description": "Display timeout in seconds after a Presence sensor detects user as inattentive",
                "values": {
                    "ac": 30,
                    "dc": 15
                }
            },
            {
                "name": "HUPRVIDEODIMAWAY",
                "description": "Dim timeout in seconds after a Presence sensor detects user as away",
                "values": {
                    "ac": 10,
                    "dc": 5
                }
            },
            {
                "name": "HUPRVIDEOIDLE",
                "description": "Display timeout in seconds after a Presence sensor detects user as away",
                "values": {
                    "ac": 30,
                    "dc": 10
                }
            },
            {
                "name": "NSENINPUTPRETIME",
                "description": "Timeout in seconds after detecting user input before considering user as present",
                "values": {
                    "ac": 60,
                    "dc": 15
                }
            },
            {
                "name": "USERPRESENCEPREDICTION",
                "description": "Specify whether to use OS User Presence detection model",
                "values": {
                    "ac": 0,
                    "dc": 0
                }
            },
            {
                "name": "STANDBYRESERVETIME",
                "description": "Timeout in seconds the device can remain idle before system starts reserving battery for standby",
                "values": {
                    "ac": 300,
                    "dc": 120
                }
            },
            {
                "name": "STANDBYRESETPERCENT",
                "description": "Battery % at which standby budget will reset",
                "values": {
                    "ac": 80,
                    "dc": 90
                }
            },
            {
                "name": "STANDBYBUDGETGRACEPERIOD",
                "description": "Grace period in seconds before taking adaptive action when the system has exceeded its standby budget",
                "values": {
                    "ac": 0,
                    "dc": 120
                }
            },
            {
                "name": "STANDBYBUDGETREFRESHINTERVAL",
                "description": "Interval in seconds between standby budget refreshes",
                "values": {
                    "ac": 0,
                    "dc": 5400
                }
            },
            {
                "name": "STANDBYBUDGETPERCENT",
                "description": "Allowed battery drain % during each budget cycle while in standby",
                "values": {
                    "ac": 0,
                    "dc": 1
                }
            },
            {
                "name": "STANDBYBUDGETREFRESHCOUNT",
                "description": "Total number of times standby budget can be refreshed before strict enforcement begins",
                "values": {
                    "ac": 0,
                    "dc": 2
                }
            },
            {
                "name": "STANDBYRESERVEGRACEPERIOD",
                "description": "Grace period in seconds before taking adaptive action when the system is below reserve battery level",
                "values": {
                    "ac": 0,
                    "dc": 60
                }
            }
        ]
    },
    {
        "category": "SUB_PROCESSOR",
        "settings": [
            {
                "name": "PROCTHROTTLEMIN",
                "description": "Minimum performance state of the system in %",
                "values": {
                    "ac": 5,
                    "dc": 1
                }
            }
        ]
    },
    {
        "category": "SUB_ENERGYSAVER",
        "settings": [
            {
                "name": "ESBRIGHTNESS",
                "description": "Brightness in % to scale to when Energy Saver is turned on",
                "values": {
                    "ac": 100,
                    "dc": 50
                }
            }
        ]
    },
    {
        "category": "SUB_PCIEXPRESS",
        "settings": [
            {
                "name": "ASPM",
                "description": "Power plan for PCI Express link",
                "values": {
                    "ac": 2,
                    "dc": 2
                }
            }
        ]
    },
    {
        "category": "SUB_NONE",
        "settings": [
            {
                "name": "PERSONALITY",
                "description": "Power plan type",
                "values": {
                    "ac": 2,
                    "dc": 0
                }
            },
            {
                "name": "DEVICEIDLE",
                "description": "Idle timeout strategy to use (Performance or Conservation)",
                "values": {
                    "ac": 0,
                    "dc": 1
                }
            },
            {
                "name": "CONSOLELOCK",
                "description": "Need to enter password when the system resumes from sleep",
                "values": {
                    "ac": 1,
                    "dc": 1
                }
            },
            {
                "name": "CONNECTIVITYINSTANDBY",
                "description": "Allow networking during standby",
                "values": {
                    "ac": 2,
                    "dc": 0
                }
            },
            {
                "name": "DISCONNECTEDSTANDBYMODE",
                "description": "Standby mode when disconnected from network",
                "values": {
                    "ac": 0,
                    "dc": 1
                }
            }
        ]
    }
]